navfitx/__init__.py
navfitx/__main__.py
navfitx/boxes.py
navfitx/constants.py
navfitx/fitrep.py
navfitx/fitrep_layout.py
navfitx/importer.py
navfitx/models.py
navfitx/overlay.py
navfitx/report.py
navfitx/utils.py
navfitx/data/blank_chief.pdf
navfitx/data/blank_eval.pdf
navfitx/data/blank_fitrep.pdf
navfitx/data/blank_summary.pdf
navfitx/gui/__init__.py
navfitx/gui/cli.py
navfitx/gui/eval.py
navfitx/gui/fitrep.py
navfitx/gui/home.py
navfitx-0.0.3a4.dist-info/licenses/LICENSE
navfitx-0.0.3a4.dist-info/METADATA
navfitx-0.0.3a4.dist-info/WHEEL
navfitx-0.0.3a4.dist-info/entry_points.txt
navfitx-0.0.3a4.dist-info/top_level.txt
navfitx-0.0.3a4.dist-info/RECORD
