Metadata-Version: 2.4
Name: navfitx
Version: 0.0.3a4
Summary: it's like NAVFIT98 but better
Project-URL: Homepage, https://github.com/tristan-white/navfitx
Requires-Python: >=3.13
License-File: LICENSE
Requires-Dist: platformdirs>=4.4.0
Requires-Dist: pydantic>=2.11.10
Requires-Dist: pymupdf>=1.26.6
Requires-Dist: pyside6>=6.9.3
Requires-Dist: reportlab>=4.4.4
Requires-Dist: sqlmodel>=0.0.27
Requires-Dist: typer>=0.19.2
Dynamic: license-file
